braulio/__init__.py
braulio/cli.py
braulio/config.py
braulio/files.py
braulio/git.py
braulio/version.py
braulio-0.3.0.dist-info/METADATA
braulio-0.3.0.dist-info/RECORD
braulio-0.3.0.dist-info/WHEEL
braulio-0.3.0.dist-info/entry_points.txt
braulio-0.3.0.dist-info/top_level.txt
