Metadata-Version: 2.1
Name: braulio
Version: 0.3.0
Summary: A command line tool to handle changelogs using Git commit messages
Home-page: https://github.com/mbarakaja/braulio
Author: José María Domínguez Moreno
Author-email: miso.0b11@gmail.com
License: MIT license
Keywords: braulio
Platform: UNKNOWN
Classifier: Development Status :: 2 - Pre-Alpha
Classifier: Intended Audience :: Developers
Classifier: License :: OSI Approved :: MIT License
Classifier: Natural Language :: English
Classifier: Programming Language :: Python :: 3.6
Requires-Dist: Click
